[{"player": {"name": "Kepa Arrizabalaga", "firstName": "", "lastName": "", "slug": "kepa-arrizabalaga", "shortName": "K. Arrizabalaga", "position": "G", "userCount": 12786, "id": 232422}, "playerName": "Kepa Arrizabalaga", "reason": "Time wasting", "rescinded": false, "id": 120939849, "time": 89, "isHome": false, "incidentClass": "yellow", "reversedPeriodTime": 2, "incidentType": "card"}, {"player": {"name": "Jude Bellingham", "slug": "jude-bellingham", "shortName": "J. Bellingham", "position": "M", "userCount": 100538, "id": 991011}, "playerName": "Jude Bellingham", "reason": "Argument", "rescinded": false, "id": 120939775, "time": 70, "isHome": false, "incidentClass": "yellow", "reversedPeriodTime": 21, "incidentType": "card"}, {"player": {"name": "Natan", "firstName": "", "lastName": "", "slug": "natan", "shortName": "Natan", "position": "D", "userCount": 1525, "id": 1015287}, "playerName": "Natan", "reason": "Foul", "rescinded": false, "id": 120939638, "time": 45, "isHome": true, "incidentClass": "yellow", "reversedPeriodTime": 1, "incidentType": "card"}, {"player": {"name": "Eduardo Camavinga", "firstName": "", "lastName": "", "slug": "camavinga-eduardo", "shortName": "E. Camavinga", "position": "M", "userCount": 30998, "id": 973887}, "playerName": "Eduardo Camavinga", "reason": "Foul", "rescinded": false, "id": 120939601, "time": 29, "isHome": false, "incidentClass": "yellow", "reversedPeriodTime": 17, "incidentType": "card"}, {"player": {"name": "Kike Barja", "slug": "kike-barja", "shortName": "K. Barja", "position": "F", "userCount": 145, "id": 591132}, "playerName": "Kike Barja", "reason": "Argument", "rescinded": false, "id": 120945246, "time": 83, "isHome": false, "incidentClass": "yellow", "reversedPeriodTime": 8, "incidentType": "card"}, {"player": {"name": "Pablo Ib\u00e1\u00f1ez Lumbreras", "firstName": "", "lastName": "", "slug": "pablo-ibanez-lumbreras", "shortName": "P. I. Lumbreras", "position": "M", "userCount": 105, "id": 1084381}, "playerName": "Pablo Ib\u00e1\u00f1ez Lumbreras", "reason": "Argument", "rescinded": false, "id": 120945261, "time": 83, "isHome": false, "incidentClass": "yellow", "reversedPeriodTime": 8, "incidentType": "card"}, {"player": {"name": "Aur\u00e9lien Tchouam\u00e9ni", "slug": "aurelien-tchouameni", "shortName": "A. Tchouam\u00e9ni", "position": "M", "userCount": 23959, "id": 859025}, "playerName": "Aur\u00e9lien Tchouam\u00e9ni", "reason": "Foul", "rescinded": false, "id": 120945065, "time": 59, "isHome": true, "incidentClass": "yellow", "reversedPeriodTime": 32, "incidentType": "card"}, {"player": {"name": "Antonio R\u00fcdiger", "firstName": "", "lastName": "", "slug": "antonio-rudiger", "shortName": "A. R\u00fcdiger", "position": "D", "userCount": 15372, "id": 142622}, "playerName": "Antonio R\u00fcdiger", "reason": "Foul", "rescinded": false, "id": 120944795, "time": 40, "isHome": true, "incidentClass": "yellow", "reversedPeriodTime": 6, "incidentType": "card"}, {"player": {"name": "Jo\u00e3o Cancelo", "slug": "joao-cancelo", "shortName": "J. Cancelo", "position": "D", "userCount": 34084, "id": 138892}, "playerName": "Jo\u00e3o Cancelo", "reason": "Argument", "rescinded": false, "id": 120950376, "time": 90, "addedTime": 8, "isHome": false, "incidentClass": "yellow", "reversedPeriodTime": 1, "incidentType": "card"}, {"player": {"name": "Carlos Neva", "slug": "neva-carlos", "shortName": "C. Neva", "position": "D", "userCount": 136, "id": 914178}, "playerName": "Carlos Neva", "reason": "Argument", "rescinded": false, "id": 120950380, "time": 90, "addedTime": 8, "isHome": true, "incidentClass": "yellow", "reversedPeriodTime": 1, "incidentType": "card"}, {"player": {"name": "Jes\u00fas Vallejo", "slug": "jesus-vallejo", "shortName": "J. Vallejo", "position": "D", "userCount": 3202, "id": 355048}, "playerName": "Jes\u00fas Vallejo", "reason": "Argument", "rescinded": false, "id": 120950344, "time": 86, "isHome": true, "incidentClass": "yellow", "reversedPeriodTime": 5, "incidentType": "card"}, {"player": {"name": "Miguel Rubio", "firstName": "", "lastName": "", "slug": "miguel-rubio", "shortName": "M. Rubio", "position": "D", "userCount": 127, "id": 934351}, "playerName": "Miguel Rubio", "reason": "Foul", "rescinded": false, "id": 120950281, "time": 68, "isHome": true, "incidentClass": "yellow", "reversedPeriodTime": 23, "incidentType": "card"}, {"player": {"name": "Bryan Zaragoza", "firstName": "", "lastName": "", "slug": "bryan-zaragoza", "shortName": "B. Zaragoza", "position": "M", "userCount": 1254, "id": 1084730}, "playerName": "Bryan Zaragoza", "reason": "Argument", "rescinded": false, "id": 120950276, "time": 65, "isHome": true, "incidentClass": "yellow", "reversedPeriodTime": 26, "incidentType": "card"}, {"playerName": "Paco Lopez", "reason": "Argument", "manager": {"name": "Paco Lopez", "slug": "paco-lopez", "shortName": "P. Lopez", "id": 788372}, "rescinded": false, "id": 120950356, "time": -5, "isHome": true, "incidentClass": "yellow", "reversedPeriodTime": 6, "incidentType": "card"}, {"player": {"name": "Sergio Ruiz Alonso", "firstName": "", "lastName": "", "slug": "sergio-ruiz-alonso", "shortName": "S. R. Alonso", "position": "M", "userCount": 99, "id": 857227}, "playerName": "Sergio Ruiz Alonso", "reason": "Argument", "rescinded": false, "id": 120950521, "time": -5, "isHome": true, "incidentClass": "yellow", "reversedPeriodTime": 6, "incidentType": "card"}, {"player": {"name": "\u00d3scar de Marcos", "firstName": "", "lastName": "", "slug": "oscar-de-marcos", "shortName": "\u00d3. de Marcos", "position": "D", "userCount": 620, "id": 52663}, "playerName": "\u00d3scar de Marcos", "reason": "Foul", "rescinded": false, "id": 120969342, "time": 89, "isHome": false, "incidentClass": "yellow", "reversedPeriodTime": 2, "incidentType": "card"}, {"player": {"name": "Marc Guiu", "firstName": "", "lastName": "", "slug": "guiu-marc", "shortName": "M. Guiu", "position": "F", "userCount": 3849, "id": 1414933}, "playerName": "Marc Guiu", "reason": "Foul", "rescinded": false, "id": 120969336, "time": 83, "isHome": true, "incidentClass": "yellow", "reversedPeriodTime": 8, "incidentType": "card"}, {"player": {"name": "Malcom Ares", "firstName": "", "lastName": "", "slug": "malcom-ares", "shortName": "M. Ares", "position": "F", "userCount": 131, "id": 1391487}, "playerName": "Malcom Ares", "reason": "Foul", "rescinded": false, "id": 120969313, "time": 73, "isHome": false, "incidentClass": "yellow", "reversedPeriodTime": 18, "incidentType": "card"}, {"player": {"name": "Oriol Romeu", "firstName": "", "lastName": "", "slug": "oriol-romeu", "shortName": "O. Romeu", "position": "M", "userCount": 4818, "id": 69416}, "playerName": "Oriol Romeu", "reason": "Foul", "rescinded": false, "id": 120969233, "time": 41, "isHome": true, "incidentClass": "yellow", "reversedPeriodTime": 5, "incidentType": "card"}, {"player": {"name": "Dani Garc\u00eda", "slug": "dani-garcia", "shortName": "D. Garc\u00eda", "position": "M", "userCount": 365, "id": 298920}, "playerName": "Dani Garc\u00eda", "reason": "Foul", "rescinded": false, "id": 120969227, "time": 37, "isHome": false, "incidentClass": "yellow", "reversedPeriodTime": 9, "incidentType": "card"}, {"player": {"name": "Gavi", "firstName": "", "lastName": "", "slug": "gavi", "shortName": "Gavi", "position": "M", "userCount": 40362, "id": 1103693}, "playerName": "Gavi", "reason": "Foul", "rescinded": false, "id": 120969193, "time": 16, "isHome": true, "incidentClass": "yellow", "reversedPeriodTime": 30, "incidentType": "card"}, {"player": {"name": "Lola Gallardo", "firstName": "", "lastName": "", "slug": "gallardo-lola", "shortName": "L. Gallardo", "position": "G", "userCount": 62, "id": 985241}, "playerName": "Lola Gallardo", "reason": "Time wasting", "rescinded": false, "id": 120939826, "time": 90, "addedTime": 2, "isHome": false, "incidentClass": "yellow", "reversedPeriodTime": 1, "incidentType": "card"}, {"player": {"name": "Kayla McKenna", "slug": "mckenna-kayla", "shortName": "K. McKenna", "position": "M", "userCount": 27, "id": 985599}, "playerName": "Kayla McKenna", "reason": "Foul", "rescinded": false, "id": 120939800, "time": 80, "isHome": true, "incidentClass": "yellow", "reversedPeriodTime": 11, "incidentType": "card"}, {"player": {"name": "Leicy Santos", "firstName": "", "lastName": "", "slug": "leicy-santos", "shortName": "L. Santos", "position": "M", "userCount": 259, "id": 796887}, "playerName": "Leicy Santos", "reason": "Argument", "rescinded": false, "id": 120939629, "time": 38, "isHome": false, "incidentClass": "yellow", "reversedPeriodTime": 8, "incidentType": "card"}, {"player": {"name": "Yenifer Gimenez", "slug": "yenifer-gimenez", "shortName": "Y. Gimenez", "position": "D", "userCount": 21, "id": 1146341}, "playerName": "Yenifer Gimenez", "reason": "Foul", "rescinded": false, "id": 120939599, "time": 31, "isHome": true, "incidentClass": "yellow", "reversedPeriodTime": 15, "incidentType": "card"}, {"player": {"name": "Ana Franco", "slug": "ana-franco", "shortName": "A. Franco", "position": "M", "userCount": 7, "id": 1009132}, "playerName": "Ana Franco", "reason": "Foul", "rescinded": false, "id": 120943775, "time": 90, "addedTime": 5, "isHome": false, "incidentClass": "yellow", "reversedPeriodTime": 1, "incidentType": "card"}, {"player": {"name": "Gabriela Garc\u00eda", "firstName": "", "lastName": "", "slug": "gabriela-garcia", "shortName": "G. Garc\u00eda", "position": "M", "userCount": 35, "id": 861622}, "playerName": "Gabriela Garc\u00eda", "reason": "Foul", "rescinded": false, "id": 120943708, "time": 76, "isHome": true, "incidentClass": "yellow", "reversedPeriodTime": 15, "incidentType": "card"}, {"player": {"name": "Cristina Mart\u00edn-Prieto", "firstName": "", "lastName": "", "slug": "cristina-martin-prieto", "shortName": "C. Mart\u00edn-Prieto", "position": "F", "userCount": 26, "id": 1009043}, "playerName": "Cristina Mart\u00edn-Prieto", "reason": "Argument", "rescinded": false, "id": 120943675, "time": 63, "isHome": false, "incidentClass": "yellow", "reversedPeriodTime": 28, "incidentType": "card"}, {"player": {"name": "Ana-Maria Crnogor\u010devi\u0107", "firstName": "", "lastName": "", "slug": "ana-maria-crnogorcevic", "shortName": "A. Crnogor\u010devi\u0107", "position": "F", "userCount": 544, "id": 68296}, "playerName": "Ana-Maria Crnogor\u010devi\u0107", "reason": "Argument", "rescinded": false, "id": 120943674, "time": 63, "isHome": true, "incidentClass": "yellow", "reversedPeriodTime": 28, "incidentType": "card"}, {"player": {"name": "Toni Payne", "firstName": "Toni Payne", "slug": "payne-toni", "shortName": "T. Payne", "position": "M", "userCount": 164, "id": 1425081}, "playerName": "Toni Payne", "reason": "Foul", "rescinded": false, "id": 120943664, "time": 60, "isHome": false, "incidentClass": "yellow", "reversedPeriodTime": 31, "incidentType": "card"}, {"player": {"name": "Amanda Sampedro", "slug": "amanda-sampedro", "shortName": "A. Sampedro", "position": "M", "userCount": 47, "id": 98109}, "playerName": "Amanda Sampedro", "reason": "Dangerous play", "rescinded": false, "id": 120943596, "time": 31, "isHome": false, "incidentClass": "yellow", "reversedPeriodTime": 15, "incidentType": "card"}, {"player": {"name": "Estefan\u00eda Banini", "slug": "estefania-banini", "shortName": "E. Banini", "position": "M", "userCount": 171, "id": 985611}, "playerName": "Estefan\u00eda Banini", "reason": "Foul", "rescinded": false, "id": 120943568, "time": 13, "isHome": true, "incidentClass": "yellow", "reversedPeriodTime": 33, "incidentType": "card"}, {"player": {"name": "Germ\u00e1n Pezzella", "slug": "german-pezzella", "shortName": "G. Pezzella", "position": "D", "userCount": 3242, "id": 158241}, "playerName": "Germ\u00e1n Pezzella", "reason": "Foul", "rescinded": false, "id": 120937144, "time": 90, "isHome": true, "incidentClass": "yellow", "reversedPeriodTime": 1, "incidentType": "card"}, {"player": {"name": "Gabriel Paulista", "slug": "gabriel-paulista", "shortName": "G. Paulista", "position": "D", "userCount": 865, "id": 124737}, "playerName": "Gabriel Paulista", "reason": "Foul", "rescinded": false, "id": 120936922, "time": 43, "isHome": false, "incidentClass": "yellow", "reversedPeriodTime": 3, "incidentType": "card"}, {"player": {"name": "Cenk \u00d6zka\u00e7ar", "firstName": "", "lastName": "", "slug": "cenk-ozkacar", "shortName": "C. \u00d6zka\u00e7ar", "position": "D", "userCount": 829, "id": 953097}, "playerName": "Cenk \u00d6zka\u00e7ar", "reason": "Foul", "rescinded": false, "id": 120936919, "time": 40, "isHome": false, "incidentClass": "yellow", "reversedPeriodTime": 6, "incidentType": "card"}, {"player": {"name": "Ayoze P\u00e9rez", "slug": "ayoze-perez", "shortName": "A. P\u00e9rez", "position": "M", "userCount": 1254, "id": 345195}, "playerName": "Ayoze P\u00e9rez", "reason": "Foul", "rescinded": false, "id": 120936836, "time": 11, "isHome": true, "incidentClass": "yellow", "reversedPeriodTime": 35, "incidentType": "card"}, {"player": {"name": "Fran P\u00e9rez", "firstName": "", "lastName": "", "slug": "fran-perez", "shortName": "F. P\u00e9rez", "position": "M", "userCount": 237, "id": 966637}, "playerName": "Fran P\u00e9rez", "reason": "Argument", "rescinded": false, "id": 120945911, "time": 69, "isHome": false, "incidentClass": "yellow", "reversedPeriodTime": 22, "incidentType": "card"}, {"player": {"name": "Samuel Costa", "slug": "samuel-costa", "shortName": "S. Costa", "position": "M", "userCount": 413, "id": 988351}, "playerName": "Samuel Costa", "reason": "Foul", "rescinded": false, "id": 120945606, "time": 36, "isHome": true, "incidentClass": "yellow", "reversedPeriodTime": 10, "incidentType": "card"}, {"player": {"name": "Giovanni Gonz\u00e1lez", "slug": "giovanni-gonzalez", "shortName": "G. Gonz\u00e1lez", "position": "D", "userCount": 412, "id": 590404}, "playerName": "Giovanni Gonz\u00e1lez", "reason": "Foul", "rescinded": false, "id": 120945487, "time": 16, "isHome": true, "incidentClass": "yellow", "reversedPeriodTime": 30, "incidentType": "card"}, {"player": {"name": "Erik Lamela", "slug": "erik-lamela", "shortName": "E. Lamela", "position": "M", "userCount": 3451, "id": 122702}, "playerName": "Erik Lamela", "reason": "Foul", "rescinded": false, "id": 120965195, "time": 90, "addedTime": 7, "isHome": true, "incidentClass": "yellow", "reversedPeriodTime": 1, "incidentType": "card"}, {"player": {"name": "Eduardo Camavinga", "firstName": "", "lastName": "", "slug": "camavinga-eduardo", "shortName": "E. Camavinga", "position": "M", "userCount": 30998, "id": 973887}, "playerName": "Eduardo Camavinga", "reason": "Foul", "rescinded": false, "id": 120965187, "time": 90, "addedTime": 4, "isHome": false, "incidentClass": "yellow", "reversedPeriodTime": 1, "incidentType": "card"}, {"player": {"name": "Boubakary Soumar\u00e9", "firstName": "", "lastName": "", "slug": "boubakary-soumare", "shortName": "B. Soumar\u00e9", "position": "M", "userCount": 1319, "id": 887581}, "playerName": "Boubakary Soumar\u00e9", "reason": "Foul", "rescinded": false, "id": 120965144, "time": 87, "isHome": true, "incidentClass": "yellow", "reversedPeriodTime": 4, "incidentType": "card"}, {"player": {"name": "Lucas Ocampos", "firstName": "", "lastName": "", "slug": "lucas-ocampos", "shortName": "L. Ocampos", "position": "M", "userCount": 4279, "id": 155702}, "playerName": "Lucas Ocampos", "reason": "Argument", "rescinded": false, "id": 120965136, "time": 85, "isHome": true, "incidentClass": "yellow", "reversedPeriodTime": 6, "incidentType": "card"}, {"player": {"name": "Vin\u00edcius J\u00fanior", "slug": "vinicius-junior", "shortName": "Vin\u00edcius", "position": "F", "userCount": 165888, "id": 868812}, "playerName": "Vin\u00edcius J\u00fanior", "reason": "Argument", "rescinded": false, "id": 120965131, "time": 85, "isHome": false, "incidentClass": "yellow", "reversedPeriodTime": 6, "incidentType": "card"}, {"player": {"name": "Jes\u00fas Navas", "firstName": "", "lastName": "", "slug": "jesus-navas", "shortName": "J. Navas", "position": "D", "userCount": 1712, "id": 11869}, "playerName": "Jes\u00fas Navas", "reason": "Argument", "rescinded": false, "id": 120965109, "time": 78, "isHome": true, "incidentClass": "yellow", "reversedPeriodTime": 13, "incidentType": "card"}, {"player": {"name": "Sergio Ramos", "firstName": "", "lastName": "", "slug": "sergio-ramos", "shortName": "S. Ramos", "position": "D", "userCount": 57392, "id": 10710}, "playerName": "Sergio Ramos", "reason": "Foul", "rescinded": false, "id": 120965107, "time": 76, "isHome": true, "incidentClass": "yellow", "reversedPeriodTime": 15, "incidentType": "card"}, {"playerName": "Carlo Ancelotti", "reason": "Argument", "manager": {"name": "Carlo Ancelotti", "slug": "carlo-ancelotti", "shortName": "C. Ancelotti", "id": 52965}, "rescinded": false, "id": 120965695, "time": -5, "isHome": false, "incidentClass": "yellow", "reversedPeriodTime": 6, "incidentType": "card"}, {"player": {"name": "Erik Lamela", "slug": "erik-lamela", "shortName": "E. Lamela", "position": "M", "userCount": 3451, "id": 122702}, "playerName": "Erik Lamela", "reason": "Simulation", "rescinded": false, "id": 120971846, "time": 76, "isHome": true, "incidentClass": "yellow", "reversedPeriodTime": 15, "incidentType": "card"}, {"player": {"name": "Jorginho", "firstName": "", "lastName": "", "slug": "jorginho", "shortName": "Jorginho", "position": "M", "userCount": 13543, "id": 132874}, "playerName": "Jorginho", "reason": "Foul", "rescinded": false, "id": 120971807, "time": 68, "isHome": false, "incidentClass": "yellow", "reversedPeriodTime": 23, "incidentType": "card"}, {"player": {"name": "Mariano D\u00edaz", "firstName": "", "lastName": "", "slug": "mariano-diaz", "shortName": "M. D\u00edaz", "position": "F", "userCount": 5072, "id": 175753}, "playerName": "Mariano D\u00edaz", "reason": "Argument", "rescinded": false, "id": 120971798, "time": 67, "isHome": true, "incidentClass": "yellow", "reversedPeriodTime": 24, "incidentType": "card"}, {"player": {"name": "\u00c9tienne Capoue", "firstName": "", "lastName": "", "slug": "etienne-capoue", "shortName": "\u00c9. Capoue", "position": "M", "userCount": 806, "id": 16701}, "playerName": "\u00c9tienne Capoue", "reason": "Foul", "rescinded": false, "id": 120948271, "time": 90, "addedTime": 10, "isHome": true, "incidentClass": "yellow", "reversedPeriodTime": 1, "incidentType": "card"}, {"player": {"name": "Ilias Akhomach", "firstName": "", "lastName": "", "slug": "ilias-akhomach", "shortName": "I. Akhomach", "position": "F", "userCount": 2818, "id": 1089108}, "playerName": "Ilias Akhomach", "reason": "Simulation", "rescinded": false, "id": 120948247, "time": 90, "addedTime": 6, "isHome": true, "incidentClass": "yellow", "reversedPeriodTime": 1, "incidentType": "card"}, {"player": {"name": "Sory Kaba", "slug": "sory-kaba", "shortName": "S. Kaba", "position": "F", "userCount": 2038, "id": 869131}, "playerName": "Sory Kaba", "reason": "Argument", "rescinded": false, "id": 120948230, "time": 90, "addedTime": 5, "isHome": false, "incidentClass": "yellow", "reversedPeriodTime": 1, "incidentType": "card"}, {"player": {"name": "Sergi Cardona", "slug": "sergi-cardona", "shortName": "S. Cardona", "position": "D", "userCount": 290, "id": 986245}, "playerName": "Sergi Cardona", "reason": "Time wasting", "rescinded": false, "id": 120948229, "time": 90, "addedTime": 4, "isHome": false, "incidentClass": "yellow", "reversedPeriodTime": 1, "incidentType": "card"}, {"player": {"name": "Kirian Rodr\u00edguez", "slug": "kirian-rodriguez", "shortName": "K. Rodr\u00edguez", "position": "M", "userCount": 246, "id": 964985}, "playerName": "Kirian Rodr\u00edguez", "reason": "Argument", "rescinded": false, "id": 120948092, "time": 72, "isHome": false, "incidentClass": "yellow", "reversedPeriodTime": 19, "incidentType": "card"}, {"player": {"name": "Marvin Park", "firstName": "", "lastName": "", "slug": "park-marvin", "shortName": "M. Park", "position": "F", "userCount": 858, "id": 960401}, "playerName": "Marvin Park", "reason": "Time wasting", "rescinded": false, "id": 120948091, "time": 68, "isHome": false, "incidentClass": "yellow", "reversedPeriodTime": 23, "incidentType": "card"}, {"player": {"name": "Dani Parejo", "firstName": "", "lastName": "", "slug": "dani-parejo", "shortName": "D. Parejo", "position": "M", "userCount": 2206, "id": 39182}, "playerName": "Dani Parejo", "reason": "Argument", "rescinded": false, "id": 120948090, "time": 68, "isHome": true, "incidentClass": "yellow", "reversedPeriodTime": 23, "incidentType": "card"}, {"player": {"name": "Y\u00e9remy Pino", "firstName": "", "lastName": "", "slug": "yeremy-pino", "shortName": "Y. Pino", "position": "M", "userCount": 2630, "id": 984624}, "playerName": "Y\u00e9remy Pino", "reason": "Foul", "rescinded": false, "id": 120947928, "time": 45, "addedTime": 1, "isHome": true, "incidentClass": "yellow", "reversedPeriodTime": 1, "incidentType": "card"}, {"player": {"name": "Santi Comesa\u00f1a", "firstName": "", "lastName": "", "slug": "santi-comesana", "shortName": "S. Comesa\u00f1a", "position": "M", "userCount": 337, "id": 843678}, "playerName": "Santi Comesa\u00f1a", "reason": "Foul", "rescinded": false, "id": 120968998, "time": 58, "isHome": true, "incidentClass": "yellow", "reversedPeriodTime": 33, "incidentType": "card"}, {"player": {"name": "Abdelkabir Abqar", "slug": "abqar-abdelkabir", "shortName": "A. Abqar", "position": "D", "userCount": 1361, "id": 1101232}, "playerName": "Abdelkabir Abqar", "reason": "Foul", "rescinded": false, "id": 120968814, "time": 36, "isHome": false, "incidentClass": "yellow", "reversedPeriodTime": 10, "incidentType": "card"}, {"player": {"name": "Kiko Femen\u00eda", "firstName": "", "lastName": "", "slug": "kiko-femenia", "shortName": "K. Femen\u00eda", "position": "D", "userCount": 186, "id": 53739}, "playerName": "Kiko Femen\u00eda", "reason": "Foul", "rescinded": false, "id": 120968807, "time": 35, "isHome": true, "incidentClass": "yellow", "reversedPeriodTime": 11, "incidentType": "card"}, {"player": {"name": "Antonio Sivera", "slug": "antonio-sivera", "shortName": "A. Sivera", "position": "G", "userCount": 204, "id": 369004}, "playerName": "Antonio Sivera", "reason": "Argument", "rescinded": false, "id": 120968794, "time": 33, "isHome": false, "incidentClass": "yellow", "reversedPeriodTime": 13, "incidentType": "card"}, {"player": {"name": "Alexander S\u00f8rloth", "slug": "alexander-sorloth", "shortName": "A. S\u00f8rloth", "position": "F", "userCount": 3902, "id": 309078}, "playerName": "Alexander S\u00f8rloth", "reason": "Off the ball foul", "rescinded": false, "id": 120968746, "time": 23, "isHome": true, "incidentClass": "yellow", "reversedPeriodTime": 23, "incidentType": "card"}, {"player": {"name": "Ander Guevara", "slug": "ander-guevara", "shortName": "A. Guevara", "position": "M", "userCount": 230, "id": 891931}, "playerName": "Ander Guevara", "reason": "Foul", "rescinded": false, "id": 120968680, "time": 14, "isHome": false, "incidentClass": "yellow", "reversedPeriodTime": 32, "incidentType": "card"}, {"player": {"name": "Alfonso Pedraza", "firstName": "", "lastName": "", "slug": "alfonso-pedraza", "shortName": "A. Pedraza", "position": "D", "userCount": 532, "id": 797290}, "playerName": "Alfonso Pedraza", "reason": "Foul", "rescinded": false, "id": 120968641, "time": 9, "isHome": true, "incidentClass": "yellow", "reversedPeriodTime": 37, "incidentType": "card"}, {"player": {"name": "Brais M\u00e9ndez", "slug": "brais-mendez", "shortName": "B. M\u00e9ndez", "position": "M", "userCount": 1743, "id": 845385}, "playerName": "Brais M\u00e9ndez", "reason": "Time wasting", "rescinded": false, "id": 120963379, "time": 90, "addedTime": 3, "isHome": true, "incidentClass": "yellow", "reversedPeriodTime": 1, "incidentType": "card"}, {"player": {"name": "Jon Pacheco", "firstName": "", "lastName": "", "slug": "jon-pacheco", "shortName": "J. Pacheco", "position": "D", "userCount": 221, "id": 934383}, "playerName": "Jon Pacheco", "reason": "Foul", "rescinded": false, "id": 120963235, "time": 71, "isHome": true, "incidentClass": "yellow", "reversedPeriodTime": 20, "incidentType": "card"}, {"player": {"name": "Igor Zubeldia", "slug": "igor-zubeldia", "shortName": "I. Zubeldia", "position": "D", "userCount": 483, "id": 838159}, "playerName": "Igor Zubeldia", "reason": "Foul", "rescinded": false, "id": 120963136, "time": 47, "isHome": true, "incidentClass": "yellow", "reversedPeriodTime": 44, "incidentType": "card"}, {"player": {"name": "Antonio S\u00e1nchez", "slug": "antonio-sanchez", "shortName": "A. S\u00e1nchez", "position": "M", "userCount": 171, "id": 949722}, "playerName": "Antonio S\u00e1nchez", "reason": "Time wasting", "rescinded": false, "id": 120963036, "time": 43, "isHome": false, "incidentClass": "yellow", "reversedPeriodTime": 3, "incidentType": "card"}, {"player": {"name": "Toni Lato", "slug": "toni-lato", "shortName": "T. Lato", "position": "D", "userCount": 321, "id": 828239}, "playerName": "Toni Lato", "reason": "Foul", "rescinded": false, "id": 120963016, "time": 41, "isHome": false, "incidentClass": "yellow", "reversedPeriodTime": 5, "incidentType": "card"}, {"player": {"name": "Jos\u00e9 Copete", "firstName": "", "lastName": "", "slug": "jose-copete", "shortName": "J. Copete", "position": "D", "userCount": 244, "id": 913695}, "playerName": "Jos\u00e9 Copete", "reason": "Foul", "rescinded": false, "id": 120962901, "time": 15, "isHome": false, "incidentClass": "yellow", "reversedPeriodTime": 31, "incidentType": "card"}, {"playerName": "Javier Aguirre", "reason": "Argument", "manager": {"name": "Javier Aguirre", "slug": "javier-aguirre", "shortName": "J. Aguirre", "id": 784504}, "rescinded": false, "id": 120963395, "time": -5, "isHome": false, "incidentClass": "yellow", "reversedPeriodTime": 6, "incidentType": "card"}, {"player": {"name": "Juan Bernat", "slug": "juan-bernat", "shortName": "J. Bernat", "position": "D", "userCount": 1749, "id": 96368}, "playerName": "Juan Bernat", "reason": "Argument", "rescinded": false, "id": 120971860, "time": 77, "isHome": true, "incidentClass": "yellow", "reversedPeriodTime": 14, "incidentType": "card"}, {"player": {"name": "Mikel Merino", "slug": "mikel-merino", "shortName": "M. Merino", "position": "M", "userCount": 1696, "id": 592010}, "playerName": "Mikel Merino", "reason": "Foul", "rescinded": false, "id": 120971849, "time": 75, "isHome": false, "incidentClass": "yellow", "reversedPeriodTime": 16, "incidentType": "card"}, {"player": {"name": "Aritz Elustondo", "slug": "aritz-elustondo", "shortName": "A. Elustondo", "position": "D", "userCount": 315, "id": 785468}, "playerName": "Aritz Elustondo", "reason": "Foul", "rescinded": false, "id": 120971810, "time": 71, "isHome": false, "incidentClass": "yellow", "reversedPeriodTime": 20, "incidentType": "card"}, {"player": {"name": "Nemanja Maksimovi\u0107", "slug": "nemanja-maksimovic", "shortName": "N. Maksimovi\u0107", "position": "M", "userCount": 1092, "id": 331449}, "playerName": "Nemanja Maksimovi\u0107", "reason": "Foul", "rescinded": false, "id": 120964535, "time": 89, "isHome": true, "incidentClass": "yellow", "reversedPeriodTime": 2, "incidentType": "card"}, {"player": {"name": "Jos\u00e9 \u00c1ngel Carmona", "firstName": "", "lastName": "", "slug": "jose-angel-carmona", "shortName": "J. \u00c1. Carmona", "position": "M", "userCount": 411, "id": 1015240}, "playerName": "Jos\u00e9 \u00c1ngel Carmona", "reason": "Foul", "rescinded": false, "id": 120964511, "time": 86, "isHome": true, "incidentClass": "yellow", "reversedPeriodTime": 5, "incidentType": "card"}, {"player": {"name": "Gast\u00f3n \u00c1lvarez", "slug": "gaston-alvarez", "shortName": "G. \u00c1lvarez", "position": "D", "userCount": 353, "id": 980578}, "playerName": "Gast\u00f3n \u00c1lvarez", "reason": "Foul", "rescinded": false, "id": 120963969, "time": 43, "isHome": true, "incidentClass": "yellow", "reversedPeriodTime": 3, "incidentType": "card"}, {"player": {"name": "Germ\u00e1n Pezzella", "slug": "german-pezzella", "shortName": "G. Pezzella", "position": "D", "userCount": 3242, "id": 158241}, "playerName": "Germ\u00e1n Pezzella", "reason": "Foul", "rescinded": false, "id": 120963956, "time": 41, "isHome": false, "incidentClass": "yellow", "reversedPeriodTime": 5, "incidentType": "card"}, {"player": {"name": "Mauro Arambarri", "slug": "mauro-arambarri", "shortName": "M. Arambarri", "position": "M", "userCount": 715, "id": 385888}, "playerName": "Mauro Arambarri", "reason": "Off the ball foul", "rescinded": false, "id": 120963932, "time": 38, "isHome": true, "incidentClass": "yellow", "reversedPeriodTime": 8, "incidentType": "card"}, {"player": {"name": "Diego Rico", "slug": "diego-rico", "shortName": "D. Rico", "position": "D", "userCount": 550, "id": 350560}, "playerName": "Diego Rico", "reason": "Foul", "rescinded": false, "id": 120963924, "time": 38, "isHome": true, "incidentClass": "yellow", "reversedPeriodTime": 8, "incidentType": "card"}, {"player": {"name": "Andr\u00e9s Guardado", "slug": "andres-guardado", "shortName": "A. Guardado", "position": "M", "userCount": 1928, "id": 14942}, "playerName": "Andr\u00e9s Guardado", "reason": "Argument", "rescinded": false, "id": 120963875, "time": 34, "isHome": false, "incidentClass": "yellow", "reversedPeriodTime": 12, "incidentType": "card"}, {"playerName": "Jos\u00e9 Bordal\u00e1s", "reason": "Argument", "manager": {"name": "Jos\u00e9 Bordal\u00e1s", "slug": "jose-bordalas", "shortName": "J. Bordal\u00e1s", "id": 94696}, "rescinded": false, "id": 120964003, "time": -5, "isHome": true, "incidentClass": "yellow", "reversedPeriodTime": 6, "incidentType": "card"}, {"player": {"name": "Andr\u00e9s Guardado", "slug": "andres-guardado", "shortName": "A. Guardado", "position": "M", "userCount": 1928, "id": 14942}, "playerName": "Andr\u00e9s Guardado", "reason": "Foul", "rescinded": false, "id": 120974072, "time": 90, "addedTime": 3, "isHome": false, "incidentClass": "yellow", "reversedPeriodTime": 1, "incidentType": "card"}, {"player": {"name": "Ayoze P\u00e9rez", "slug": "ayoze-perez", "shortName": "A. P\u00e9rez", "position": "M", "userCount": 1254, "id": 345195}, "playerName": "Ayoze P\u00e9rez", "reason": "Argument", "rescinded": false, "id": 120974006, "time": 60, "isHome": false, "incidentClass": "yellow", "reversedPeriodTime": 31, "incidentType": "card"}, {"player": {"name": "Yannick Gomis", "slug": "yannick-gomis", "shortName": "Y. Gomis", "position": "F", "userCount": 215, "id": 845121}, "playerName": "Yannick Gomis", "reason": "Argument", "rescinded": false, "id": 120973994, "time": 55, "isHome": true, "incidentClass": "yellow", "reversedPeriodTime": 36, "incidentType": "card"}, {"player": {"name": "Leo Bengtsson", "slug": "leo-bengtsson", "shortName": "L. Bengtsson", "position": "F", "userCount": 91, "id": 860157}, "playerName": "Leo Bengtsson", "reason": "Foul", "rescinded": false, "id": 120973922, "time": 28, "isHome": true, "incidentClass": "yellow", "reversedPeriodTime": 18, "incidentType": "card"}, {"player": {"name": "Igor Zubeldia", "slug": "igor-zubeldia", "shortName": "I. Zubeldia", "position": "D", "userCount": 483, "id": 838159}, "playerName": "Igor Zubeldia", "reason": "Foul", "rescinded": false, "id": 120933298, "time": 77, "isHome": true, "incidentClass": "yellow", "reversedPeriodTime": 14, "incidentType": "card"}, {"player": {"name": "Mikel Merino", "slug": "mikel-merino", "shortName": "M. Merino", "position": "M", "userCount": 1696, "id": 592010}, "playerName": "Mikel Merino", "reason": "Foul", "rescinded": false, "id": 120933114, "time": 44, "isHome": true, "incidentClass": "yellow", "reversedPeriodTime": 2, "incidentType": "card"}, {"player": {"name": "Daniel Vivian", "firstName": "", "lastName": "", "slug": "daniel-vivian", "shortName": "D. Vivian", "position": "D", "userCount": 566, "id": 910978}, "playerName": "Daniel Vivian", "reason": "Foul", "rescinded": false, "id": 120933115, "time": 44, "isHome": false, "incidentClass": "yellow", "reversedPeriodTime": 2, "incidentType": "card"}, {"player": {"name": "Ander Herrera", "slug": "ander-herrera", "shortName": "A. Herrera", "position": "M", "userCount": 2704, "id": 82474}, "playerName": "Ander Herrera", "reason": "Foul", "rescinded": false, "id": 120933051, "time": 29, "isHome": false, "incidentClass": "yellow", "reversedPeriodTime": 17, "incidentType": "card"}, {"player": {"name": "\u00d3scar de Marcos", "firstName": "", "lastName": "", "slug": "oscar-de-marcos", "shortName": "\u00d3. de Marcos", "position": "D", "userCount": 620, "id": 52663}, "playerName": "\u00d3scar de Marcos", "reason": "Foul", "rescinded": false, "id": 120943124, "time": 84, "isHome": true, "incidentClass": "yellow", "reversedPeriodTime": 7, "incidentType": "card"}, {"player": {"name": "Ander Herrera", "slug": "ander-herrera", "shortName": "A. Herrera", "position": "M", "userCount": 2704, "id": 82474}, "playerName": "Ander Herrera", "reason": "Foul", "rescinded": false, "id": 120943048, "time": 52, "isHome": true, "incidentClass": "yellow", "reversedPeriodTime": 39, "incidentType": "card"}, {"player": {"name": "Mauro Arambarri", "slug": "mauro-arambarri", "shortName": "M. Arambarri", "position": "M", "userCount": 715, "id": 385888}, "playerName": "Mauro Arambarri", "reason": "Foul", "rescinded": false, "id": 120949915, "time": 90, "addedTime": 6, "isHome": false, "incidentClass": "yellow", "reversedPeriodTime": 1, "incidentType": "card"}, {"player": {"name": "Diego Rico", "slug": "diego-rico", "shortName": "D. Rico", "position": "D", "userCount": 550, "id": 350560}, "playerName": "Diego Rico", "reason": "Foul", "rescinded": false, "id": 120949890, "time": 81, "isHome": false, "incidentClass": "yellow", "reversedPeriodTime": 10, "incidentType": "card"}, {"player": {"name": "Fran Beltr\u00e1n", "slug": "fran-beltran", "shortName": "F. Beltr\u00e1n", "position": "M", "userCount": 576, "id": 835484}, "playerName": "Fran Beltr\u00e1n", "reason": "Foul", "rescinded": false, "id": 120949758, "time": 53, "isHome": true, "incidentClass": "yellow", "reversedPeriodTime": 38, "incidentType": "card"}, {"player": {"name": "Carles Ale\u00f1\u00e1", "firstName": "", "lastName": "", "slug": "carles-alena", "shortName": "C. Ale\u00f1\u00e1", "position": "M", "userCount": 2013, "id": 794937}, "playerName": "Carles Ale\u00f1\u00e1", "reason": "Foul", "rescinded": false, "id": 120949537, "time": 38, "isHome": false, "incidentClass": "yellow", "reversedPeriodTime": 8, "incidentType": "card"}, {"player": {"name": "Jaime Mata", "slug": "jaime-mata", "shortName": "J. Mata", "position": "M", "userCount": 424, "id": 351140}, "playerName": "Jaime Mata", "reason": "Foul", "rescinded": false, "id": 120949509, "time": 31, "isHome": false, "incidentClass": "yellow", "reversedPeriodTime": 15, "incidentType": "card"}, {"player": {"name": "Djen\u00e9", "slug": "djene", "shortName": "Djen\u00e9", "position": "D", "userCount": 780, "id": 307702}, "playerName": "Djen\u00e9", "reason": "Foul", "rescinded": false, "id": 120949494, "time": 27, "isHome": false, "incidentClass": "yellow", "reversedPeriodTime": 19, "incidentType": "card"}, {"player": {"name": "Nemanja Maksimovi\u0107", "slug": "nemanja-maksimovic", "shortName": "N. Maksimovi\u0107", "position": "M", "userCount": 1092, "id": 331449}, "playerName": "Nemanja Maksimovi\u0107", "reason": "Foul", "rescinded": false, "id": 120949499, "time": 13, "isHome": false, "incidentClass": "yellow", "reversedPeriodTime": 33, "incidentType": "card"}, {"player": {"name": "Domingos Duarte", "firstName": "", "lastName": "", "slug": "domingos-duarte", "shortName": "D. Duarte", "position": "D", "userCount": 590, "id": 576276}, "playerName": "Domingos Duarte", "reason": "Foul", "rescinded": false, "id": 120949364, "time": 9, "isHome": false, "incidentClass": "yellow", "reversedPeriodTime": 37, "incidentType": "card"}, {"player": {"name": "Jos\u00e9 \u00c1ngel Carmona", "firstName": "", "lastName": "", "slug": "jose-angel-carmona", "shortName": "J. \u00c1. Carmona", "position": "M", "userCount": 411, "id": 1015240}, "playerName": "Jos\u00e9 \u00c1ngel Carmona", "reason": "Argument", "rescinded": false, "id": 120950617, "time": -5, "isHome": false, "incidentClass": "yellow", "reversedPeriodTime": 6, "incidentType": "card"}, {"player": {"name": "Miguel Rodr\u00edguez", "firstName": "", "lastName": "", "slug": "miguel-rodriguez", "shortName": "M. Rodr\u00edguez", "position": "F", "userCount": 137, "id": 1014118}, "playerName": "Miguel Rodr\u00edguez", "reason": "Argument", "rescinded": false, "id": 120965667, "time": 87, "isHome": true, "incidentClass": "yellow", "reversedPeriodTime": 4, "incidentType": "card"}, {"player": {"name": "Rodrigo Riquelme", "firstName": "", "lastName": "", "slug": "rodrigo-riquelme", "shortName": "R. Riquelme", "position": "M", "userCount": 1621, "id": 989113}, "playerName": "Rodrigo Riquelme", "reason": "Argument", "rescinded": false, "id": 120965668, "time": 87, "isHome": false, "incidentClass": "yellow", "reversedPeriodTime": 4, "incidentType": "card"}, {"player": {"name": "Sa\u00fal \u00d1\u00edguez", "firstName": "", "lastName": "", "slug": "saul-niguez", "shortName": "S. \u00d1\u00edguez", "position": "M", "userCount": 3816, "id": 116955}, "playerName": "Sa\u00fal \u00d1\u00edguez", "reason": "Foul", "rescinded": false, "id": 120965592, "time": 54, "isHome": false, "incidentClass": "yellow", "reversedPeriodTime": 37, "incidentType": "card"}, {"player": {"name": "Carl Starfelt", "slug": "carl-starfelt", "shortName": "C. Starfelt", "position": "D", "userCount": 344, "id": 360718}, "playerName": "Carl Starfelt", "reason": "Foul", "rescinded": false, "id": 120965579, "time": 51, "isHome": true, "incidentClass": "yellow", "reversedPeriodTime": 40, "incidentType": "card"}, {"player": {"name": "\u00d3scar Mingueza", "firstName": "", "lastName": "", "slug": "oscar-mingueza", "shortName": "\u00d3. Mingueza", "position": "D", "userCount": 2799, "id": 859773}, "playerName": "\u00d3scar Mingueza", "reason": "Argument", "rescinded": false, "id": 120965402, "time": 30, "isHome": true, "incidentClass": "yellow", "reversedPeriodTime": 16, "incidentType": "card"}, {"player": {"name": "\u00d3scar de Marcos", "firstName": "", "lastName": "", "slug": "oscar-de-marcos", "shortName": "\u00d3. de Marcos", "position": "D", "userCount": 620, "id": 52663}, "playerName": "\u00d3scar de Marcos", "reason": "Foul", "rescinded": false, "id": 120943124, "time": 84, "isHome": true, "incidentClass": "yellow", "reversedPeriodTime": 7, "incidentType": "card"}, {"player": {"name": "Ander Herrera", "slug": "ander-herrera", "shortName": "A. Herrera", "position": "M", "userCount": 2704, "id": 82474}, "playerName": "Ander Herrera", "reason": "Foul", "rescinded": false, "id": 120943048, "time": 52, "isHome": true, "incidentClass": "yellow", "reversedPeriodTime": 39, "incidentType": "card"}, {"player": {"name": "L\u00e9o Baptist\u00e3o", "firstName": "", "lastName": "", "slug": "leo-baptistao", "shortName": "L\u00e9o Baptist\u00e3o", "position": "F", "userCount": 695, "id": 252857}, "playerName": "L\u00e9o Baptist\u00e3o", "reason": "Foul", "rescinded": false, "id": 120968338, "time": 74, "isHome": false, "incidentClass": "yellow", "reversedPeriodTime": 17, "incidentType": "card"}, {"player": {"name": "David L\u00f3pez", "slug": "david-lopez", "shortName": "D. L\u00f3pez", "position": "D", "userCount": 595, "id": 135116}, "playerName": "David L\u00f3pez", "reason": "Foul", "rescinded": false, "id": 120968063, "time": 45, "addedTime": 4, "isHome": true, "incidentClass": "yellow", "reversedPeriodTime": 1, "incidentType": "card"}, {"player": {"name": "Lucas Robertone", "slug": "lucas-robertone", "shortName": "L. Robertone", "position": "M", "userCount": 994, "id": 848926}, "playerName": "Lucas Robertone", "reason": "Foul", "rescinded": false, "id": 120967885, "time": 26, "isHome": false, "incidentClass": "yellow", "reversedPeriodTime": 20, "incidentType": "card"}, {"player": {"name": "Kiko Femen\u00eda", "firstName": "", "lastName": "", "slug": "kiko-femenia", "shortName": "K. Femen\u00eda", "position": "D", "userCount": 186, "id": 53739}, "playerName": "Kiko Femen\u00eda", "reason": "Time wasting", "rescinded": false, "id": 120931065, "time": 74, "isHome": false, "incidentClass": "yellow", "reversedPeriodTime": 17, "incidentType": "card"}, {"player": {"name": "Y\u00e9remy Pino", "firstName": "", "lastName": "", "slug": "yeremy-pino", "shortName": "Y. Pino", "position": "M", "userCount": 2630, "id": 984624}, "playerName": "Y\u00e9remy Pino", "reason": "Foul", "rescinded": false, "id": 120931031, "time": 67, "isHome": false, "incidentClass": "yellow", "reversedPeriodTime": 24, "incidentType": "card"}, {"player": {"name": "Filip J\u00f6rgensen", "firstName": "", "lastName": "", "slug": "filip-jorgensen", "shortName": "F. J\u00f6rgensen", "position": "G", "userCount": 650, "id": 962053}, "playerName": "Filip J\u00f6rgensen", "reason": "Time wasting", "rescinded": false, "id": 120931000, "time": 62, "isHome": false, "incidentClass": "yellow", "reversedPeriodTime": 29, "incidentType": "card"}, {"player": {"name": "Mason Greenwood", "slug": "mason-greenwood", "shortName": "M. Greenwood", "position": "M", "userCount": 33827, "id": 942116}, "playerName": "Mason Greenwood", "reason": "Foul", "rescinded": false, "id": 120930943, "time": 53, "isHome": true, "incidentClass": "yellow", "reversedPeriodTime": 38, "incidentType": "card"}, {"player": {"name": "\u00d3scar Rodr\u00edguez", "firstName": "", "lastName": "", "slug": "oscar-rodriguez", "shortName": "\u00d3. Rodr\u00edguez", "position": "M", "userCount": 918, "id": 794948}, "playerName": "\u00d3scar Rodr\u00edguez", "reason": "Foul", "rescinded": false, "id": 120930783, "time": 30, "isHome": true, "incidentClass": "yellow", "reversedPeriodTime": 16, "incidentType": "card"}, {"player": {"name": "Alfonso Pedraza", "firstName": "", "lastName": "", "slug": "alfonso-pedraza", "shortName": "A. Pedraza", "position": "D", "userCount": 532, "id": 797290}, "playerName": "Alfonso Pedraza", "reason": "Foul", "rescinded": false, "id": 120930689, "time": 5, "isHome": false, "incidentClass": "yellow", "reversedPeriodTime": 41, "incidentType": "card"}, {"player": {"name": "Mauro Arambarri", "slug": "mauro-arambarri", "shortName": "M. Arambarri", "position": "M", "userCount": 715, "id": 385888}, "playerName": "Mauro Arambarri", "reason": "Foul", "rescinded": false, "id": 120949915, "time": 90, "addedTime": 6, "isHome": false, "incidentClass": "yellow", "reversedPeriodTime": 1, "incidentType": "card"}, {"player": {"name": "Diego Rico", "slug": "diego-rico", "shortName": "D. Rico", "position": "D", "userCount": 550, "id": 350560}, "playerName": "Diego Rico", "reason": "Foul", "rescinded": false, "id": 120949890, "time": 81, "isHome": false, "incidentClass": "yellow", "reversedPeriodTime": 10, "incidentType": "card"}, {"player": {"name": "Fran Beltr\u00e1n", "slug": "fran-beltran", "shortName": "F. Beltr\u00e1n", "position": "M", "userCount": 576, "id": 835484}, "playerName": "Fran Beltr\u00e1n", "reason": "Foul", "rescinded": false, "id": 120949758, "time": 53, "isHome": true, "incidentClass": "yellow", "reversedPeriodTime": 38, "incidentType": "card"}, {"player": {"name": "Carles Ale\u00f1\u00e1", "firstName": "", "lastName": "", "slug": "carles-alena", "shortName": "C. Ale\u00f1\u00e1", "position": "M", "userCount": 2013, "id": 794937}, "playerName": "Carles Ale\u00f1\u00e1", "reason": "Foul", "rescinded": false, "id": 120949537, "time": 38, "isHome": false, "incidentClass": "yellow", "reversedPeriodTime": 8, "incidentType": "card"}, {"player": {"name": "Jaime Mata", "slug": "jaime-mata", "shortName": "J. Mata", "position": "M", "userCount": 424, "id": 351140}, "playerName": "Jaime Mata", "reason": "Foul", "rescinded": false, "id": 120949509, "time": 31, "isHome": false, "incidentClass": "yellow", "reversedPeriodTime": 15, "incidentType": "card"}, {"player": {"name": "Djen\u00e9", "slug": "djene", "shortName": "Djen\u00e9", "position": "D", "userCount": 780, "id": 307702}, "playerName": "Djen\u00e9", "reason": "Foul", "rescinded": false, "id": 120949494, "time": 27, "isHome": false, "incidentClass": "yellow", "reversedPeriodTime": 19, "incidentType": "card"}, {"player": {"name": "Nemanja Maksimovi\u0107", "slug": "nemanja-maksimovic", "shortName": "N. Maksimovi\u0107", "position": "M", "userCount": 1092, "id": 331449}, "playerName": "Nemanja Maksimovi\u0107", "reason": "Foul", "rescinded": false, "id": 120949499, "time": 13, "isHome": false, "incidentClass": "yellow", "reversedPeriodTime": 33, "incidentType": "card"}, {"player": {"name": "Domingos Duarte", "firstName": "", "lastName": "", "slug": "domingos-duarte", "shortName": "D. Duarte", "position": "D", "userCount": 590, "id": 576276}, "playerName": "Domingos Duarte", "reason": "Foul", "rescinded": false, "id": 120949364, "time": 9, "isHome": false, "incidentClass": "yellow", "reversedPeriodTime": 37, "incidentType": "card"}, {"player": {"name": "Jos\u00e9 \u00c1ngel Carmona", "firstName": "", "lastName": "", "slug": "jose-angel-carmona", "shortName": "J. \u00c1. Carmona", "position": "M", "userCount": 411, "id": 1015240}, "playerName": "Jos\u00e9 \u00c1ngel Carmona", "reason": "Argument", "rescinded": false, "id": 120950617, "time": -5, "isHome": false, "incidentClass": "yellow", "reversedPeriodTime": 6, "incidentType": "card"}, {"player": {"name": "Fran P\u00e9rez", "firstName": "", "lastName": "", "slug": "fran-perez", "shortName": "F. P\u00e9rez", "position": "M", "userCount": 237, "id": 966637}, "playerName": "Fran P\u00e9rez", "reason": "Argument", "rescinded": false, "id": 120945911, "time": 69, "isHome": false, "incidentClass": "yellow", "reversedPeriodTime": 22, "incidentType": "card"}, {"player": {"name": "Samuel Costa", "slug": "samuel-costa", "shortName": "S. Costa", "position": "M", "userCount": 413, "id": 988351}, "playerName": "Samuel Costa", "reason": "Foul", "rescinded": false, "id": 120945606, "time": 36, "isHome": true, "incidentClass": "yellow", "reversedPeriodTime": 10, "incidentType": "card"}, {"player": {"name": "Giovanni Gonz\u00e1lez", "slug": "giovanni-gonzalez", "shortName": "G. Gonz\u00e1lez", "position": "D", "userCount": 412, "id": 590404}, "playerName": "Giovanni Gonz\u00e1lez", "reason": "Foul", "rescinded": false, "id": 120945487, "time": 16, "isHome": true, "incidentClass": "yellow", "reversedPeriodTime": 30, "incidentType": "card"}, {"player": {"name": "Brais M\u00e9ndez", "slug": "brais-mendez", "shortName": "B. M\u00e9ndez", "position": "M", "userCount": 1743, "id": 845385}, "playerName": "Brais M\u00e9ndez", "reason": "Time wasting", "rescinded": false, "id": 120963379, "time": 90, "addedTime": 3, "isHome": true, "incidentClass": "yellow", "reversedPeriodTime": 1, "incidentType": "card"}, {"player": {"name": "Jon Pacheco", "firstName": "", "lastName": "", "slug": "jon-pacheco", "shortName": "J. Pacheco", "position": "D", "userCount": 221, "id": 934383}, "playerName": "Jon Pacheco", "reason": "Foul", "rescinded": false, "id": 120963235, "time": 71, "isHome": true, "incidentClass": "yellow", "reversedPeriodTime": 20, "incidentType": "card"}, {"player": {"name": "Igor Zubeldia", "slug": "igor-zubeldia", "shortName": "I. Zubeldia", "position": "D", "userCount": 483, "id": 838159}, "playerName": "Igor Zubeldia", "reason": "Foul", "rescinded": false, "id": 120963136, "time": 47, "isHome": true, "incidentClass": "yellow", "reversedPeriodTime": 44, "incidentType": "card"}, {"player": {"name": "Antonio S\u00e1nchez", "slug": "antonio-sanchez", "shortName": "A. S\u00e1nchez", "position": "M", "userCount": 171, "id": 949722}, "playerName": "Antonio S\u00e1nchez", "reason": "Time wasting", "rescinded": false, "id": 120963036, "time": 43, "isHome": false, "incidentClass": "yellow", "reversedPeriodTime": 3, "incidentType": "card"}, {"player": {"name": "Toni Lato", "slug": "toni-lato", "shortName": "T. Lato", "position": "D", "userCount": 321, "id": 828239}, "playerName": "Toni Lato", "reason": "Foul", "rescinded": false, "id": 120963016, "time": 41, "isHome": false, "incidentClass": "yellow", "reversedPeriodTime": 5, "incidentType": "card"}, {"player": {"name": "Jos\u00e9 Copete", "firstName": "", "lastName": "", "slug": "jose-copete", "shortName": "J. Copete", "position": "D", "userCount": 244, "id": 913695}, "playerName": "Jos\u00e9 Copete", "reason": "Foul", "rescinded": false, "id": 120962901, "time": 15, "isHome": false, "incidentClass": "yellow", "reversedPeriodTime": 31, "incidentType": "card"}, {"playerName": "Javier Aguirre", "reason": "Argument", "manager": {"name": "Javier Aguirre", "slug": "javier-aguirre", "shortName": "J. Aguirre", "id": 784504}, "rescinded": false, "id": 120963395, "time": -5, "isHome": false, "incidentClass": "yellow", "reversedPeriodTime": 6, "incidentType": "card"}, {"player": {"name": "Ibrahima K\u00e9b\u00e9", "slug": "ibrahima-kebe", "shortName": "I. K\u00e9b\u00e9", "position": "M", "userCount": 150, "id": 1031566}, "playerName": "Ibrahima K\u00e9b\u00e9", "reason": "Foul", "rescinded": false, "id": 120944313, "time": 90, "isHome": false, "incidentClass": "yellow", "reversedPeriodTime": 1, "incidentType": "card"}, {"player": {"name": "Yangel Herrera", "slug": "yangel-herrera", "shortName": "Y. Herrera", "position": "M", "userCount": 1875, "id": 839585}, "playerName": "Yangel Herrera", "reason": "Foul", "rescinded": false, "id": 120944012, "time": 45, "addedTime": 3, "isHome": false, "incidentClass": "yellow", "reversedPeriodTime": 1, "incidentType": "card"}, {"player": {"name": "Aleix Garc\u00eda", "firstName": "", "lastName": "", "slug": "aleix-garcia", "shortName": "A. Garc\u00eda", "position": "M", "userCount": 1955, "id": 796047}, "playerName": "Aleix Garc\u00eda", "reason": "Foul", "rescinded": false, "id": 120943799, "time": 4, "isHome": false, "incidentClass": "yellow", "reversedPeriodTime": 42, "incidentType": "card"}, {"player": {"name": "Rub\u00e9n Alcaraz", "slug": "ruben-alcaraz", "shortName": "R. Alcaraz", "position": "M", "userCount": 346, "id": 259339}, "playerName": "Rub\u00e9n Alcaraz", "reason": "Foul", "rescinded": false, "id": 120943794, "time": 2, "isHome": true, "incidentClass": "yellow", "reversedPeriodTime": 44, "incidentType": "card"}, {"player": {"name": "L\u00e9o Baptist\u00e3o", "firstName": "", "lastName": "", "slug": "leo-baptistao", "shortName": "L\u00e9o Baptist\u00e3o", "position": "F", "userCount": 695, "id": 252857}, "playerName": "L\u00e9o Baptist\u00e3o", "reason": "Foul", "rescinded": false, "id": 120968338, "time": 74, "isHome": false, "incidentClass": "yellow", "reversedPeriodTime": 17, "incidentType": "card"}, {"player": {"name": "David L\u00f3pez", "slug": "david-lopez", "shortName": "D. L\u00f3pez", "position": "D", "userCount": 595, "id": 135116}, "playerName": "David L\u00f3pez", "reason": "Foul", "rescinded": false, "id": 120968063, "time": 45, "addedTime": 4, "isHome": true, "incidentClass": "yellow", "reversedPeriodTime": 1, "incidentType": "card"}, {"player": {"name": "Lucas Robertone", "slug": "lucas-robertone", "shortName": "L. Robertone", "position": "M", "userCount": 994, "id": 848926}, "playerName": "Lucas Robertone", "reason": "Foul", "rescinded": false, "id": 120967885, "time": 26, "isHome": false, "incidentClass": "yellow", "reversedPeriodTime": 20, "incidentType": "card"}, {"player": {"name": "Gonzalo Villar", "firstName": "", "lastName": "", "slug": "gonzalo-villar", "shortName": "G. Villar", "position": "M", "userCount": 496, "id": 914765}, "playerName": "Gonzalo Villar", "reason": "Foul", "rescinded": false, "id": 120934998, "time": 88, "isHome": false, "incidentClass": "yellow", "reversedPeriodTime": 3, "incidentType": "card"}, {"player": {"name": "Sergio Akieme", "slug": "sergio-akieme", "shortName": "S. Akieme", "position": "D", "userCount": 438, "id": 827942}, "playerName": "Sergio Akieme", "reason": "Time wasting", "rescinded": false, "id": 120934958, "time": 82, "isHome": true, "incidentClass": "yellow", "reversedPeriodTime": 9, "incidentType": "card"}, {"player": {"name": "Arnau Puigmal", "slug": "arnau-puigmal", "shortName": "A. Puigmal", "position": "M", "userCount": 237, "id": 910023}, "playerName": "Arnau Puigmal", "reason": "Foul", "rescinded": false, "id": 120934839, "time": 65, "isHome": true, "incidentClass": "yellow", "reversedPeriodTime": 26, "incidentType": "card"}, {"playerName": "Paco Lopez", "reason": "Argument", "manager": {"name": "Paco Lopez", "slug": "paco-lopez", "shortName": "P. Lopez", "id": 788372}, "rescinded": false, "id": 120934876, "time": -5, "isHome": false, "incidentClass": "yellow", "reversedPeriodTime": 6, "incidentType": "card"}, {"player": {"name": "Jo\u00e3o Cancelo", "slug": "joao-cancelo", "shortName": "J. Cancelo", "position": "D", "userCount": 34084, "id": 138892}, "playerName": "Jo\u00e3o Cancelo", "reason": "Argument", "rescinded": false, "id": 120950376, "time": 90, "addedTime": 8, "isHome": false, "incidentClass": "yellow", "reversedPeriodTime": 1, "incidentType": "card"}, {"player": {"name": "Carlos Neva", "slug": "neva-carlos", "shortName": "C. Neva", "position": "D", "userCount": 136, "id": 914178}, "playerName": "Carlos Neva", "reason": "Argument", "rescinded": false, "id": 120950380, "time": 90, "addedTime": 8, "isHome": true, "incidentClass": "yellow", "reversedPeriodTime": 1, "incidentType": "card"}, {"player": {"name": "Jes\u00fas Vallejo", "slug": "jesus-vallejo", "shortName": "J. Vallejo", "position": "D", "userCount": 3202, "id": 355048}, "playerName": "Jes\u00fas Vallejo", "reason": "Argument", "rescinded": false, "id": 120950344, "time": 86, "isHome": true, "incidentClass": "yellow", "reversedPeriodTime": 5, "incidentType": "card"}, {"player": {"name": "Miguel Rubio", "firstName": "", "lastName": "", "slug": "miguel-rubio", "shortName": "M. Rubio", "position": "D", "userCount": 127, "id": 934351}, "playerName": "Miguel Rubio", "reason": "Foul", "rescinded": false, "id": 120950281, "time": 68, "isHome": true, "incidentClass": "yellow", "reversedPeriodTime": 23, "incidentType": "card"}, {"player": {"name": "Bryan Zaragoza", "firstName": "", "lastName": "", "slug": "bryan-zaragoza", "shortName": "B. Zaragoza", "position": "M", "userCount": 1254, "id": 1084730}, "playerName": "Bryan Zaragoza", "reason": "Argument", "rescinded": false, "id": 120950276, "time": 65, "isHome": true, "incidentClass": "yellow", "reversedPeriodTime": 26, "incidentType": "card"}, {"playerName": "Paco Lopez", "reason": "Argument", "manager": {"name": "Paco Lopez", "slug": "paco-lopez", "shortName": "P. Lopez", "id": 788372}, "rescinded": false, "id": 120950356, "time": -5, "isHome": true, "incidentClass": "yellow", "reversedPeriodTime": 6, "incidentType": "card"}, {"player": {"name": "Sergio Ruiz Alonso", "firstName": "", "lastName": "", "slug": "sergio-ruiz-alonso", "shortName": "S. R. Alonso", "position": "M", "userCount": 99, "id": 857227}, "playerName": "Sergio Ruiz Alonso", "reason": "Argument", "rescinded": false, "id": 120950521, "time": -5, "isHome": true, "incidentClass": "yellow", "reversedPeriodTime": 6, "incidentType": "card"}, {"player": {"name": "Rominigue Kouam\u00e9", "firstName": "", "lastName": "", "slug": "rominigue-kouame", "shortName": "R. Kouam\u00e9", "position": "M", "userCount": 372, "id": 846446}, "playerName": "Rominigue Kouam\u00e9", "reason": "Foul", "rescinded": false, "id": 120937152, "time": 90, "addedTime": 3, "isHome": false, "incidentClass": "yellow", "reversedPeriodTime": 1, "incidentType": "card"}, {"player": {"name": "Rub\u00e9n Sobrino", "slug": "ruben-sobrino", "shortName": "R. Sobrino", "position": "M", "userCount": 241, "id": 329563}, "playerName": "Rub\u00e9n Sobrino", "reason": "Argument", "rescinded": false, "id": 120937149, "time": 90, "addedTime": 2, "isHome": false, "incidentClass": "yellow", "reversedPeriodTime": 1, "incidentType": "card"}, {"player": {"name": "Roger Mart\u00ed", "slug": "roger-marti", "shortName": "R. Mart\u00ed", "position": "F", "userCount": 430, "id": 212074}, "playerName": "Roger Mart\u00ed", "reason": "Persistent fouling", "rescinded": false, "id": 120936905, "time": 39, "isHome": false, "incidentClass": "yellow", "reversedPeriodTime": 7, "incidentType": "card"}, {"player": {"name": "Koke", "firstName": "", "lastName": "", "slug": "koke", "shortName": "Koke", "position": "M", "userCount": 3609, "id": 84539}, "playerName": "Koke", "reason": "Argument", "rescinded": false, "id": 120936843, "time": 12, "isHome": true, "incidentClass": "yellow", "reversedPeriodTime": 34, "incidentType": "card"}, {"player": {"name": "Ibrahima K\u00e9b\u00e9", "slug": "ibrahima-kebe", "shortName": "I. K\u00e9b\u00e9", "position": "M", "userCount": 150, "id": 1031566}, "playerName": "Ibrahima K\u00e9b\u00e9", "reason": "Foul", "rescinded": false, "id": 120944313, "time": 90, "isHome": false, "incidentClass": "yellow", "reversedPeriodTime": 1, "incidentType": "card"}, {"player": {"name": "Yangel Herrera", "slug": "yangel-herrera", "shortName": "Y. Herrera", "position": "M", "userCount": 1875, "id": 839585}, "playerName": "Yangel Herrera", "reason": "Foul", "rescinded": false, "id": 120944012, "time": 45, "addedTime": 3, "isHome": false, "incidentClass": "yellow", "reversedPeriodTime": 1, "incidentType": "card"}, {"player": {"name": "Aleix Garc\u00eda", "firstName": "", "lastName": "", "slug": "aleix-garcia", "shortName": "A. Garc\u00eda", "position": "M", "userCount": 1955, "id": 796047}, "playerName": "Aleix Garc\u00eda", "reason": "Foul", "rescinded": false, "id": 120943799, "time": 4, "isHome": false, "incidentClass": "yellow", "reversedPeriodTime": 42, "incidentType": "card"}, {"player": {"name": "Rub\u00e9n Alcaraz", "slug": "ruben-alcaraz", "shortName": "R. Alcaraz", "position": "M", "userCount": 346, "id": 259339}, "playerName": "Rub\u00e9n Alcaraz", "reason": "Foul", "rescinded": false, "id": 120943794, "time": 2, "isHome": true, "incidentClass": "yellow", "reversedPeriodTime": 44, "incidentType": "card"}, {"player": {"name": "Aleksandar Sedlar", "slug": "aleksandar-sedlar", "shortName": "A. Sedlar", "position": "D", "userCount": 134, "id": 799195}, "playerName": "Aleksandar Sedlar", "reason": "Foul", "rescinded": false, "id": 120949906, "time": 90, "addedTime": 3, "isHome": true, "incidentClass": "yellow", "reversedPeriodTime": 1, "incidentType": "card"}, {"player": {"name": "Isco", "slug": "isco", "shortName": "Isco", "position": "M", "userCount": 13960, "id": 103417}, "playerName": "Isco", "reason": "Argument", "rescinded": false, "id": 120949899, "time": 89, "isHome": false, "incidentClass": "yellow", "reversedPeriodTime": 2, "incidentType": "card"}, {"player": {"name": "Samuel Omorodion", "firstName": "Samuel Omorodion", "slug": "omorodion-samuel", "shortName": "S. Omorodion", "position": "F", "userCount": 551, "id": 1503836}, "playerName": "Samuel Omorodion", "reason": "Foul", "rescinded": false, "id": 120949882, "time": 83, "isHome": true, "incidentClass": "yellow", "reversedPeriodTime": 8, "incidentType": "card"}, {"player": {"name": "Abner Vin\u00edcius", "firstName": "", "lastName": "", "slug": "abner-vinicius", "shortName": "Abner Vin\u00edcius", "position": "D", "userCount": 714, "id": 973838}, "playerName": "Abner Vin\u00edcius", "reason": "Foul", "rescinded": false, "id": 120949841, "time": 71, "isHome": false, "incidentClass": "yellow", "reversedPeriodTime": 20, "incidentType": "card"}, {"player": {"name": "Luis Rioja", "slug": "luis-rioja", "shortName": "L. Rioja", "position": "M", "userCount": 496, "id": 900433}, "playerName": "Luis Rioja", "reason": "Argument", "rescinded": false, "id": 120949797, "time": 62, "isHome": true, "incidentClass": "yellow", "reversedPeriodTime": 29, "incidentType": "card"}, {"player": {"name": "Guido Rodr\u00edguez", "slug": "guido-rodriguez", "shortName": "G. Rodr\u00edguez", "position": "M", "userCount": 3836, "id": 609752}, "playerName": "Guido Rodr\u00edguez", "reason": "Foul", "rescinded": false, "id": 120949534, "time": 34, "isHome": false, "incidentClass": "yellow", "reversedPeriodTime": 12, "incidentType": "card"}, {"player": {"name": "Santi Comesa\u00f1a", "firstName": "", "lastName": "", "slug": "santi-comesana", "shortName": "S. Comesa\u00f1a", "position": "M", "userCount": 337, "id": 843678}, "playerName": "Santi Comesa\u00f1a", "reason": "Foul", "rescinded": false, "id": 120968998, "time": 58, "isHome": true, "incidentClass": "yellow", "reversedPeriodTime": 33, "incidentType": "card"}, {"player": {"name": "Abdelkabir Abqar", "slug": "abqar-abdelkabir", "shortName": "A. Abqar", "position": "D", "userCount": 1361, "id": 1101232}, "playerName": "Abdelkabir Abqar", "reason": "Foul", "rescinded": false, "id": 120968814, "time": 36, "isHome": false, "incidentClass": "yellow", "reversedPeriodTime": 10, "incidentType": "card"}, {"player": {"name": "Kiko Femen\u00eda", "firstName": "", "lastName": "", "slug": "kiko-femenia", "shortName": "K. Femen\u00eda", "position": "D", "userCount": 186, "id": 53739}, "playerName": "Kiko Femen\u00eda", "reason": "Foul", "rescinded": false, "id": 120968807, "time": 35, "isHome": true, "incidentClass": "yellow", "reversedPeriodTime": 11, "incidentType": "card"}, {"player": {"name": "Antonio Sivera", "slug": "antonio-sivera", "shortName": "A. Sivera", "position": "G", "userCount": 204, "id": 369004}, "playerName": "Antonio Sivera", "reason": "Argument", "rescinded": false, "id": 120968794, "time": 33, "isHome": false, "incidentClass": "yellow", "reversedPeriodTime": 13, "incidentType": "card"}, {"player": {"name": "Alexander S\u00f8rloth", "slug": "alexander-sorloth", "shortName": "A. S\u00f8rloth", "position": "F", "userCount": 3902, "id": 309078}, "playerName": "Alexander S\u00f8rloth", "reason": "Off the ball foul", "rescinded": false, "id": 120968746, "time": 23, "isHome": true, "incidentClass": "yellow", "reversedPeriodTime": 23, "incidentType": "card"}, {"player": {"name": "Ander Guevara", "slug": "ander-guevara", "shortName": "A. Guevara", "position": "M", "userCount": 230, "id": 891931}, "playerName": "Ander Guevara", "reason": "Foul", "rescinded": false, "id": 120968680, "time": 14, "isHome": false, "incidentClass": "yellow", "reversedPeriodTime": 32, "incidentType": "card"}, {"player": {"name": "Alfonso Pedraza", "firstName": "", "lastName": "", "slug": "alfonso-pedraza", "shortName": "A. Pedraza", "position": "D", "userCount": 532, "id": 797290}, "playerName": "Alfonso Pedraza", "reason": "Foul", "rescinded": false, "id": 120968641, "time": 9, "isHome": true, "incidentClass": "yellow", "reversedPeriodTime": 37, "incidentType": "card"}, {"player": {"name": "Omar Mascarell", "slug": "omar-mascarell", "shortName": "O. Mascarell", "position": "M", "userCount": 321, "id": 255999}, "playerName": "Omar Mascarell", "reason": "Argument", "rescinded": false, "id": 120932203, "time": 90, "addedTime": 10, "isHome": false, "incidentClass": "yellow", "reversedPeriodTime": 1, "incidentType": "card"}, {"player": {"name": "Amath Ndiaye", "slug": "amath-ndiaye", "shortName": "A. Ndiaye", "position": "F", "userCount": 473, "id": 845168}, "playerName": "Amath Ndiaye", "reason": "Foul", "rescinded": false, "id": 120932184, "time": 90, "addedTime": 6, "isHome": false, "incidentClass": "yellow", "reversedPeriodTime": 1, "incidentType": "card"}, {"player": {"name": "Giovanni Gonz\u00e1lez", "slug": "giovanni-gonzalez", "shortName": "G. Gonz\u00e1lez", "position": "D", "userCount": 412, "id": 590404}, "playerName": "Giovanni Gonz\u00e1lez", "reason": "Argument", "rescinded": false, "id": 120932189, "time": 90, "addedTime": 5, "isHome": false, "incidentClass": "yellow", "reversedPeriodTime": 1, "incidentType": "card"}, {"player": {"name": "Ra\u00fal de Tom\u00e1s", "firstName": "", "lastName": "", "slug": "raul-de-tomas", "shortName": "R. de Tom\u00e1s", "position": "F", "userCount": 1728, "id": 138387}, "playerName": "Ra\u00fal de Tom\u00e1s", "reason": "Argument", "rescinded": false, "id": 120932173, "time": 90, "addedTime": 4, "isHome": true, "incidentClass": "yellow", "reversedPeriodTime": 1, "incidentType": "card"}, {"player": {"name": "Sergi Darder", "slug": "sergi-darder", "shortName": "S. Darder", "position": "M", "userCount": 873, "id": 110783}, "playerName": "Sergi Darder", "reason": "Foul", "rescinded": false, "id": 120932112, "time": 83, "isHome": false, "incidentClass": "yellow", "reversedPeriodTime": 8, "incidentType": "card"}, {"player": {"name": "Unai L\u00f3pez", "firstName": "", "lastName": "", "slug": "unai-lopez", "shortName": "U. L\u00f3pez", "position": "M", "userCount": 256, "id": 588566}, "playerName": "Unai L\u00f3pez", "reason": "Foul", "rescinded": false, "id": 120931606, "time": 43, "isHome": true, "incidentClass": "yellow", "reversedPeriodTime": 3, "incidentType": "card"}, {"player": {"name": "Jaume Costa", "slug": "jaume-costa", "shortName": "J. Costa", "position": "D", "userCount": 184, "id": 44577}, "playerName": "Jaume Costa", "reason": "Argument", "rescinded": false, "id": 120932174, "time": -5, "isHome": false, "incidentClass": "yellow", "reversedPeriodTime": 6, "incidentType": "card"}, {"player": {"name": "Jes\u00fas Navas", "firstName": "", "lastName": "", "slug": "jesus-navas", "shortName": "J. Navas", "position": "D", "userCount": 1712, "id": 11869}, "playerName": "Jes\u00fas Navas", "reason": "Foul", "rescinded": false, "id": 120946601, "time": 84, "isHome": true, "incidentClass": "yellow", "reversedPeriodTime": 7, "incidentType": "card"}, {"player": {"name": "Kike P\u00e9rez", "slug": "kike-perez", "shortName": "K. P\u00e9rez", "position": "M", "userCount": 161, "id": 857178}, "playerName": "Kike P\u00e9rez", "reason": "Foul", "rescinded": false, "id": 120946595, "time": 84, "isHome": false, "incidentClass": "yellow", "reversedPeriodTime": 7, "incidentType": "card"}, {"player": {"name": "Aridane Hern\u00e1ndez", "slug": "aridane-hernandez", "shortName": "A. Hern\u00e1ndez", "position": "D", "userCount": 261, "id": 41013}, "playerName": "Aridane Hern\u00e1ndez", "reason": "Foul", "rescinded": false, "id": 120946562, "time": 74, "isHome": false, "incidentClass": "yellow", "reversedPeriodTime": 17, "incidentType": "card"}, {"player": {"name": "Suso", "firstName": "", "lastName": "", "slug": "suso", "shortName": "Suso", "position": "M", "userCount": 1991, "id": 96370}, "playerName": "Suso", "reason": "Foul", "rescinded": false, "id": 120946550, "time": 67, "isHome": true, "incidentClass": "yellow", "reversedPeriodTime": 24, "incidentType": "card"}, {"player": {"name": "Djibril Sow", "slug": "djibril-sow", "shortName": "D. Sow", "position": "M", "userCount": 1060, "id": 799054}, "playerName": "Djibril Sow", "reason": "Foul", "rescinded": false, "id": 120946434, "time": 45, "addedTime": 3, "isHome": true, "incidentClass": "yellow", "reversedPeriodTime": 1, "incidentType": "card"}, {"player": {"name": "Nemanja Gudelj", "firstName": "", "lastName": "", "slug": "nemanja-gudelj", "shortName": "N. Gudelj", "position": "D", "userCount": 1581, "id": 68332}, "playerName": "Nemanja Gudelj", "reason": "Foul", "rescinded": false, "id": 120946375, "time": 36, "isHome": true, "incidentClass": "yellow", "reversedPeriodTime": 10, "incidentType": "card"}, {"player": {"name": "Joan Jord\u00e1n", "firstName": "", "lastName": "", "slug": "joan-jordan", "shortName": "J. Jord\u00e1n", "position": "M", "userCount": 822, "id": 591750}, "playerName": "Joan Jord\u00e1n", "reason": "Argument", "rescinded": false, "id": 120946631, "time": -5, "isHome": true, "incidentClass": "yellow", "reversedPeriodTime": 6, "incidentType": "card"}, {"player": {"name": "Kike Barja", "slug": "kike-barja", "shortName": "K. Barja", "position": "F", "userCount": 145, "id": 591132}, "playerName": "Kike Barja", "reason": "Argument", "rescinded": false, "id": 120945246, "time": 83, "isHome": false, "incidentClass": "yellow", "reversedPeriodTime": 8, "incidentType": "card"}, {"player": {"name": "Pablo Ib\u00e1\u00f1ez Lumbreras", "firstName": "", "lastName": "", "slug": "pablo-ibanez-lumbreras", "shortName": "P. I. Lumbreras", "position": "M", "userCount": 105, "id": 1084381}, "playerName": "Pablo Ib\u00e1\u00f1ez Lumbreras", "reason": "Argument", "rescinded": false, "id": 120945261, "time": 83, "isHome": false, "incidentClass": "yellow", "reversedPeriodTime": 8, "incidentType": "card"}, {"player": {"name": "Aur\u00e9lien Tchouam\u00e9ni", "slug": "aurelien-tchouameni", "shortName": "A. Tchouam\u00e9ni", "position": "M", "userCount": 23959, "id": 859025}, "playerName": "Aur\u00e9lien Tchouam\u00e9ni", "reason": "Foul", "rescinded": false, "id": 120945065, "time": 59, "isHome": true, "incidentClass": "yellow", "reversedPeriodTime": 32, "incidentType": "card"}, {"player": {"name": "Antonio R\u00fcdiger", "firstName": "", "lastName": "", "slug": "antonio-rudiger", "shortName": "A. R\u00fcdiger", "position": "D", "userCount": 15372, "id": 142622}, "playerName": "Antonio R\u00fcdiger", "reason": "Foul", "rescinded": false, "id": 120944795, "time": 40, "isHome": true, "incidentClass": "yellow", "reversedPeriodTime": 6, "incidentType": "card"}, {"player": {"name": "\u00c9tienne Capoue", "firstName": "", "lastName": "", "slug": "etienne-capoue", "shortName": "\u00c9. Capoue", "position": "M", "userCount": 806, "id": 16701}, "playerName": "\u00c9tienne Capoue", "reason": "Foul", "rescinded": false, "id": 120948271, "time": 90, "addedTime": 10, "isHome": true, "incidentClass": "yellow", "reversedPeriodTime": 1, "incidentType": "card"}, {"player": {"name": "Ilias Akhomach", "firstName": "", "lastName": "", "slug": "ilias-akhomach", "shortName": "I. Akhomach", "position": "F", "userCount": 2818, "id": 1089108}, "playerName": "Ilias Akhomach", "reason": "Simulation", "rescinded": false, "id": 120948247, "time": 90, "addedTime": 6, "isHome": true, "incidentClass": "yellow", "reversedPeriodTime": 1, "incidentType": "card"}, {"player": {"name": "Sory Kaba", "slug": "sory-kaba", "shortName": "S. Kaba", "position": "F", "userCount": 2038, "id": 869131}, "playerName": "Sory Kaba", "reason": "Argument", "rescinded": false, "id": 120948230, "time": 90, "addedTime": 5, "isHome": false, "incidentClass": "yellow", "reversedPeriodTime": 1, "incidentType": "card"}, {"player": {"name": "Sergi Cardona", "slug": "sergi-cardona", "shortName": "S. Cardona", "position": "D", "userCount": 290, "id": 986245}, "playerName": "Sergi Cardona", "reason": "Time wasting", "rescinded": false, "id": 120948229, "time": 90, "addedTime": 4, "isHome": false, "incidentClass": "yellow", "reversedPeriodTime": 1, "incidentType": "card"}, {"player": {"name": "Kirian Rodr\u00edguez", "slug": "kirian-rodriguez", "shortName": "K. Rodr\u00edguez", "position": "M", "userCount": 246, "id": 964985}, "playerName": "Kirian Rodr\u00edguez", "reason": "Argument", "rescinded": false, "id": 120948092, "time": 72, "isHome": false, "incidentClass": "yellow", "reversedPeriodTime": 19, "incidentType": "card"}, {"player": {"name": "Marvin Park", "firstName": "", "lastName": "", "slug": "park-marvin", "shortName": "M. Park", "position": "F", "userCount": 858, "id": 960401}, "playerName": "Marvin Park", "reason": "Time wasting", "rescinded": false, "id": 120948091, "time": 68, "isHome": false, "incidentClass": "yellow", "reversedPeriodTime": 23, "incidentType": "card"}, {"player": {"name": "Dani Parejo", "firstName": "", "lastName": "", "slug": "dani-parejo", "shortName": "D. Parejo", "position": "M", "userCount": 2206, "id": 39182}, "playerName": "Dani Parejo", "reason": "Argument", "rescinded": false, "id": 120948090, "time": 68, "isHome": true, "incidentClass": "yellow", "reversedPeriodTime": 23, "incidentType": "card"}, {"player": {"name": "Y\u00e9remy Pino", "firstName": "", "lastName": "", "slug": "yeremy-pino", "shortName": "Y. Pino", "position": "M", "userCount": 2630, "id": 984624}, "playerName": "Y\u00e9remy Pino", "reason": "Foul", "rescinded": false, "id": 120947928, "time": 45, "addedTime": 1, "isHome": true, "incidentClass": "yellow", "reversedPeriodTime": 1, "incidentType": "card"}, {"player": {"name": "M\u00e1ximo Perrone", "firstName": "Maximo Perrone", "lastName": "", "slug": "maximo-perrone", "shortName": "M. Perrone", "position": "M", "userCount": 4909, "id": 1086286}, "playerName": "M\u00e1ximo Perrone", "reason": "Foul", "rescinded": false, "id": 120967510, "time": 90, "addedTime": 5, "isHome": true, "incidentClass": "yellow", "reversedPeriodTime": 1, "incidentType": "card"}, {"player": {"name": "Alex Su\u00e1rez", "slug": "alex-suarez", "shortName": "A. Su\u00e1rez", "position": "D", "userCount": 183, "id": 914848}, "playerName": "Alex Su\u00e1rez", "reason": "Foul", "rescinded": false, "id": 120967483, "time": 90, "isHome": true, "incidentClass": "yellow", "reversedPeriodTime": 1, "incidentType": "card"}, {"player": {"name": "\u00d3scar Valent\u00edn", "firstName": "", "lastName": "", "slug": "oscar-valentin", "shortName": "\u00d3. Valent\u00edn", "position": "M", "userCount": 321, "id": 900008}, "playerName": "\u00d3scar Valent\u00edn", "reason": "Foul", "rescinded": false, "id": 120967413, "time": 86, "isHome": false, "incidentClass": "yellow", "reversedPeriodTime": 5, "incidentType": "card"}, {"player": {"name": "Sergio Camello", "firstName": "", "lastName": "", "slug": "sergio-camello", "shortName": "S. Camello", "position": "F", "userCount": 826, "id": 910024}, "playerName": "Sergio Camello", "reason": "Argument", "rescinded": false, "id": 120967367, "time": 79, "isHome": false, "incidentClass": "yellow", "reversedPeriodTime": 12, "incidentType": "card"}, {"player": {"name": "Javier Mu\u00f1oz", "slug": "javier-munoz", "shortName": "J. Mu\u00f1oz", "position": "M", "userCount": 114, "id": 353154}, "playerName": "Javier Mu\u00f1oz", "reason": "Foul", "rescinded": false, "id": 120967355, "time": 77, "isHome": true, "incidentClass": "yellow", "reversedPeriodTime": 14, "incidentType": "card"}, {"player": {"name": "Sa\u00fal Coco", "firstName": "", "lastName": "", "slug": "saul-coco", "shortName": "S. Coco", "position": "D", "userCount": 208, "id": 964466}, "playerName": "Sa\u00fal Coco", "reason": "Foul", "rescinded": false, "id": 120966868, "time": 20, "isHome": true, "incidentClass": "yellow", "reversedPeriodTime": 26, "incidentType": "card"}, {"playerName": "Francisco Rodriguez", "reason": "Argument", "manager": {"name": "Francisco Rodriguez", "slug": "francisco-rodriguez", "shortName": "F. Rodriguez", "id": 334245}, "rescinded": false, "id": 120967512, "time": -5, "isHome": false, "incidentClass": "yellow", "reversedPeriodTime": 6, "incidentType": "card"}]